qbc/__init__.py
qbc/learners.py
qbc/util.py
qbc-0.0.1.dist-info/METADATA
qbc-0.0.1.dist-info/WHEEL
qbc-0.0.1.dist-info/licenses/LICENSE
qbc-0.0.1.dist-info/RECORD
