Metadata-Version: 2.1
Name: qbc
Version: 0.0.1
Summary: A implementation of QBC Active Learning Algorithums
Author-email: Benjamin Pierce <bgpierc@sandia.gov>
License-File: LICENSE
Classifier: License :: OSI Approved :: MIT License
Classifier: Operating System :: OS Independent
Classifier: Programming Language :: Python :: 3
Requires-Python: >=3.6
